pyefun/__init__.py
pyefun/excel/__init__.py
pyefun/excel/excel_openpyxl.py
pyefun/excel/excel_openpyxl2.py
pyefun/excel/excel_xlwr.py
pyefun/ffmpeg/__init__.py
pyefun/ffmpeg/ffmpeg.py
pyefun/seleniumUtil/__init__.py
pyefun/seleniumUtil/browserUtil.py
pyefun/seleniumUtil/seleniumUtil.py
pyefun/seleniumUtil/seleniumUtil_test.py
pyefun/wxefun/__init__.py
pyefun/人工智能/ChatGPT.py
pyefun/人工智能/ONNX分类模型推理.py
pyefun/人工智能/ONNX分类模型推理_test.py
pyefun/人工智能/__init__.py
pyefun/人工智能/aiserver.py
pyefun/人工智能/markdown模块.py
pyefun/人工智能/openai_test.py
pyefun/人工智能/图像生成.py
pyefun/人工智能/通用文字识别.py
pyefun/人工智能/通用文字识别_test.py
pyefun/图像处理/__init__.py
pyefun/图像处理/图像处理.py
pyefun/图像处理/图像处理PIL.py
pyefun/图像处理/图像处理_Test.py
pyefun/图像处理/图像处理函数.py
pyefun/数据库/__init__.py
pyefun/数据库/mongo数据库.py
pyefun/数据库/mysql数据库.py
pyefun/数据库/peeweeUtil.py
pyefun/数据库/redis工具类.py
pyefun/数据库/sqlite工具类.py
pyefun/核心支持库/__init__.py
pyefun/核心支持库/公用函数.py
pyefun/核心支持库/数组操作.py
pyefun/核心支持库/数组操作_test.py
pyefun/核心支持库/文本操作.py
pyefun/核心支持库/文本操作_test.py
pyefun/核心支持库/日期时间操作.py
pyefun/核心支持库/日期时间操作_test.py
pyefun/核心支持库/时钟.py
pyefun/核心支持库/时钟_test.py
pyefun/核心支持库/磁盘操作.py
pyefun/核心支持库/磁盘操作_test.py
pyefun/核心支持库/算数运算.py
pyefun/核心支持库/算数运算_test.py
pyefun/核心支持库/类型转换.py
pyefun/核心支持库/类型转换_test.py
pyefun/核心支持库/系统处理.py
pyefun/核心支持库/系统处理_test.py
pyefun/核心支持库/编码转换.py
pyefun/核心支持库/编码转换_test.py
pyefun/核心易函数支持库/__init__.py
pyefun/核心易函数支持库/json函数.py
pyefun/核心易函数支持库/json函数_test.py
pyefun/核心易函数支持库/实用函数.py
pyefun/核心易函数支持库/文本操作实用函数.py
pyefun/核心易函数支持库/文本操作实用函数_test.py
pyefun/核心易函数支持库/时间统计.py
pyefun/核心易函数支持库/时间统计_test.py
pyefun/核心易函数支持库/正则表达式.py
pyefun/核心易函数支持库/正则表达式_test.py
pyefun/核心易函数支持库/正则表达式实用函数.py
pyefun/核心易函数支持库/正则表达式实用函数_test.py
pyefun/核心易函数支持库/环境变量.py
pyefun/核心易函数支持库/环境变量_test.py
pyefun/核心易函数支持库/线程操作.py
pyefun/核心易函数支持库/线程操作_test.py
pyefun/核心易函数支持库/网络实用函数.py
pyefun/核心易函数支持库/网络实用函数_test.py
pyefun/核心易函数支持库/网络请求.py
pyefun/核心易函数支持库/网络请求_test.py
pyefun/核心易函数支持库/进程池.py
pyefun/核心易函数支持库/进程池_test.py
pyefun/核心易函数支持库/配置项.py
pyefun/核心易函数支持库/配置项_test.py
pyefun-1.3.13.dist-info/LICENSE
pyefun-1.3.13.dist-info/METADATA
pyefun-1.3.13.dist-info/WHEEL
pyefun-1.3.13.dist-info/top_level.txt
pyefun-1.3.13.dist-info/RECORD
